chdb/__init__.py
chdb/__main__.py
chdb/_chdb.abi3.so
chdb/libpybind11nonlimitedapi_chdb_3.10.so
chdb/libpybind11nonlimitedapi_chdb_3.11.so
chdb/libpybind11nonlimitedapi_chdb_3.12.so
chdb/libpybind11nonlimitedapi_chdb_3.13.so
chdb/libpybind11nonlimitedapi_chdb_3.14.so
chdb/libpybind11nonlimitedapi_chdb_3.8.so
chdb/libpybind11nonlimitedapi_chdb_3.9.so
chdb/rwabc.py
chdb/dataframe/__init__.py
chdb/dataframe/query.py
chdb/dbapi/__init__.py
chdb/dbapi/connections.py
chdb/dbapi/converters.py
chdb/dbapi/cursors.py
chdb/dbapi/err.py
chdb/dbapi/times.py
chdb/dbapi/constants/FIELD_TYPE.py
chdb/dbapi/constants/__init__.py
chdb/session/__init__.py
chdb/session/state.py
chdb/state/__init__.py
chdb/state/sqlitelike.py
chdb/udf/__init__.py
chdb/udf/udf.py
chdb/utils/__init__.py
chdb/utils/trace.py
chdb/utils/types.py
chdb-3.7.2.dist-info/LICENSE.txt
chdb-3.7.2.dist-info/METADATA
chdb-3.7.2.dist-info/WHEEL
chdb-3.7.2.dist-info/top_level.txt
chdb-3.7.2.dist-info/RECORD
