Metadata-Version: 2.1
Name: chdb
Version: 3.7.2
Summary: chDB is an in-process OLAP SQL Engine powered by ClickHouse
Home-page: https://github.com/chdb-io/chdb
Author: auxten
Author-email: chDB Team <auxten@clickhouse.com>
License: Apache-2.0
Project-URL: Homepage, https://clickhouse.com/chdb
Project-URL: Documentation, https://chdb.readthedocs.io/en/latest/index.html
Project-URL: Repository, https://github.com/chdb-io/chdb
Project-URL: Changelog, https://github.com/chdb-io/chdb/releases
Project-URL: Issues, https://github.com/chdb-io/chdb/issues
Keywords: chdb,clickhouse,olap,analytics,database,sql
Platform: Mac
Platform: Linux
Classifier: Development Status :: 5 - Production/Stable
Classifier: Environment :: Plugins
Classifier: Intended Audience :: Developers
Classifier: License :: OSI Approved :: Apache Software License
Classifier: Operating System :: MacOS :: MacOS X
Classifier: Operating System :: POSIX :: Linux
Classifier: Programming Language :: Python :: 3
Classifier: Programming Language :: Python :: 3.8
Classifier: Programming Language :: Python :: 3.9
Classifier: Programming Language :: Python :: 3.10
Classifier: Programming Language :: Python :: 3.11
Classifier: Programming Language :: Python :: 3.12
Classifier: Programming Language :: Python :: 3.13
Classifier: Programming Language :: Python :: 3.14
Classifier: Programming Language :: C++
Classifier: Topic :: Software Development :: Libraries
Classifier: Topic :: Database
Classifier: Topic :: Scientific/Engineering
Requires-Python: >=3.8
License-File: LICENSE.txt
Requires-Dist: pandas>=2.0.0
Requires-Dist: pyarrow>=13.0.0
Provides-Extra: ci
Requires-Dist: cibuildwheel; extra == "ci"
Provides-Extra: dev
Requires-Dist: pytest; extra == "dev"
Requires-Dist: pytest-cov; extra == "dev"
Provides-Extra: publish
Requires-Dist: twine; extra == "publish"
Requires-Dist: wheel; extra == "publish"
